apkleaks/__init__.py
apkleaks/apkleaks.py
apkleaks/cli.py
apkleaks/colors.py
apkleaks/utils.py
config/notkeyhacks.json
config/regexes.json
apkleaks-2.6.3.dist-info/LICENSE
apkleaks-2.6.3.dist-info/METADATA
apkleaks-2.6.3.dist-info/WHEEL
apkleaks-2.6.3.dist-info/entry_points.txt
apkleaks-2.6.3.dist-info/top_level.txt
apkleaks-2.6.3.dist-info/RECORD
