Metadata-Version: 2.1
Name: apkleaks
Version: 2.6.3
Summary: Scanning APK file for URIs, endpoints & secrets.
Author-email: dwisiswant0 <me@dw1.io>
License: Apache License 2.0
Project-URL: Homepage, https://github.com/dwisiswant0/apkleaks/
Classifier: Development Status :: 3 - Alpha
Classifier: Natural Language :: English
Classifier: Topic :: Security
Classifier: Topic :: Utilities
Requires-Python: >=3.8
License-File: LICENSE
Requires-Dist: pyaxmlparser >=0.3.24
